odoo8_addon_web_environment_ribbon-8.0.1.0.0-py2.7-nspkg.pth
odoo_addons/web_environment_ribbon/__openerp__.py
odoo_addons/web_environment_ribbon/__init__.py
odoo_addons/web_environment_ribbon/README.rst
odoo_addons/web_environment_ribbon/view/base_view.xml
odoo_addons/web_environment_ribbon/data/ribbon_data.xml
odoo_addons/web_environment_ribbon/static/description/screenshot.png
odoo_addons/web_environment_ribbon/static/description/icon.png
odoo_addons/web_environment_ribbon/static/src/js/ribbon.js
odoo_addons/web_environment_ribbon/static/src/css/ribbon.css
odoo8_addon_web_environment_ribbon-8.0.1.0.0.dist-info/top_level.txt
odoo8_addon_web_environment_ribbon-8.0.1.0.0.dist-info/WHEEL
odoo8_addon_web_environment_ribbon-8.0.1.0.0.dist-info/RECORD
odoo8_addon_web_environment_ribbon-8.0.1.0.0.dist-info/metadata.json
odoo8_addon_web_environment_ribbon-8.0.1.0.0.dist-info/DESCRIPTION.rst
odoo8_addon_web_environment_ribbon-8.0.1.0.0.dist-info/METADATA
odoo8_addon_web_environment_ribbon-8.0.1.0.0.dist-info/namespace_packages.txt
